twitter_text/__init__.py
twitter_text/autolink.py
twitter_text/extractor.py
twitter_text/highlighter.py
twitter_text/regex.py
twitter_text/unicode.py
twitter_text/validation.py
twitter_text/templatetags/__init__.py
twitter_text/templatetags/twitterize.py
twitter_text-3.0.dist-info/DESCRIPTION.rst
twitter_text-3.0.dist-info/METADATA
twitter_text-3.0.dist-info/RECORD
twitter_text-3.0.dist-info/WHEEL
twitter_text-3.0.dist-info/metadata.json
twitter_text-3.0.dist-info/top_level.txt
